o2mcp/__init__.py
o2mcp-0.0.3.dist-info/METADATA
o2mcp-0.0.3.dist-info/WHEEL
o2mcp-0.0.3.dist-info/entry_points.txt
o2mcp-0.0.3.dist-info/RECORD
